{"_type":"export","__export_format":4,"__export_date":"2022-01-23T23:28:52.304Z","__export_source":"insomnia.desktop.app:v2021.7.2","resources":[{"_id":"req_bbae31507f6b40f49957563dec58390b","parentId":"fld_08a10223d7d7455296913aa5649d802e","modified":1642979820718,"created":1642957020494,"url":"{{ _.users_api_url }}users/61edd3a64c34d3f8fbc7cae9","name":"delete by user id","description":"","method":"DELETE","body":{},"parameters":[],"headers":[{"id":"pair_a61f421b03684fc0a082b2c5756492b1","name":"Authorization","value":"Bearer {% response 'body', 'req_defd2d9e88dc499bb439090875f18ef6', 'b64::JC5hY2Nlc3NfdG9rZW4=::46b', 'when-expired', 900 %}","description":""}],"authentication":{},"metaSortKey":-1642957020494,"isPrivate":false,"settingStoreCookies":true,"settingSendCookies":true,"settingDisableRenderRequestBody":false,"settingEncodeUrl":true,"settingRebuildPath":true,"settingFollowRedirects":"global","_type":"request"},{"_id":"fld_08a10223d7d7455296913aa5649d802e","parentId":"wrk_98588b23176c4ecbb49eb37605ada3d7","modified":1642949945588,"created":1642949945588,"name":"Users","description":"","environment":{},"environmentPropertyOrder":null,"metaSortKey":-1642949945588,"_type":"request_group"},{"_id":"wrk_98588b23176c4ecbb49eb37605ada3d7","parentId":null,"modified":1642901441196,"created":1642901441196,"name":"ilia-challenge","description":"","scope":"collection","_type":"workspace"},{"_id":"req_53244a25cee04cf8b43236d96678a2b5","parentId":"fld_08a10223d7d7455296913aa5649d802e","modified":1642979821874,"created":1642956695928,"url":"{{ _.users_api_url }}users/61ede14f77302924b82c3e80","name":"by user id","description":"","method":"GET","body":{},"parameters":[],"headers":[{"id":"pair_f708d79664ea4baaa6b84958733fb04f","name":"Authorization","value":"Bearer {% response 'body', 'req_defd2d9e88dc499bb439090875f18ef6', 'b64::JC5hY2Nlc3NfdG9rZW4=::46b', 'when-expired', 900 %}","description":""}],"authentication":{},"metaSortKey":-1642956695928,"isPrivate":false,"settingStoreCookies":true,"settingSendCookies":true,"settingDisableRenderRequestBody":false,"settingEncodeUrl":true,"settingRebuildPath":true,"settingFollowRedirects":"global","_type":"request"},{"_id":"req_105dc94ae3c14a9bbedb795949160b3b","parentId":"fld_08a10223d7d7455296913aa5649d802e","modified":1642979822343,"created":1642955956785,"url":"{{ _.users_api_url }}users","name":"list admin","description":"","method":"GET","body":{},"parameters":[],"headers":[{"id":"pair_d9c2e994641344eb94b9d852ce3c5d53","name":"Authorization","value":"Bearer {% response 'body', 'req_defd2d9e88dc499bb439090875f18ef6', 'b64::JC5hY2Nlc3NfdG9rZW4=::46b', 'when-expired', 900 %}","description":""}],"authentication":{},"metaSortKey":-1642955956785,"isPrivate":false,"settingStoreCookies":true,"settingSendCookies":true,"settingDisableRenderRequestBody":false,"settingEncodeUrl":true,"settingRebuildPath":true,"settingFollowRedirects":"global","_type":"request"},{"_id":"req_7dc659186ba9465a86d60c07f5c26fa1","parentId":"fld_08a10223d7d7455296913aa5649d802e","modified":1642979822606,"created":1642957742030,"url":"{{ _.users_api_url }}users","name":"update by user id","description":"","method":"PATCH","body":{"mimeType":"application/json","text":"{\n  \"first_name\": \"Test\"\n}"},"parameters":[],"headers":[{"name":"Content-Type","value":"application/json","id":"pair_573ba3acb7734d59ab7fbc74b0a1b62a"},{"id":"pair_b7b29d5244d44290bb85e00db6fcd16a","name":"Authorization","value":"Bearer {% response 'body', 'req_defd2d9e88dc499bb439090875f18ef6', 'b64::JC5hY2Nlc3NfdG9rZW4=::46b', 'when-expired', 900 %}","description":""}],"authentication":{},"metaSortKey":-1642953054898,"isPrivate":false,"settingStoreCookies":true,"settingSendCookies":true,"settingDisableRenderRequestBody":false,"settingEncodeUrl":true,"settingRebuildPath":true,"settingFollowRedirects":"global","_type":"request"},{"_id":"req_9b0eee8f26a64913821f4e083269a241","parentId":"fld_08a10223d7d7455296913aa5649d802e","modified":1642979853380,"created":1642950153010,"url":"{{ _.users_api_url }}users","name":"create","description":"","method":"POST","body":{"mimeType":"application/json","text":"{\n  \"first_name\": \"User\",\n  \"last_name\": \"Admin\",\n  \"password\": \"user_admin\",\n  \"email\": \"user.admin@email.com\",\n\t\"isAdmin\": true\n}"},"parameters":[],"headers":[{"name":"Content-Type","value":"application/json","id":"pair_eda041efe8984213803324e5fe31f38d"}],"authentication":{},"metaSortKey":-1642950153011,"isPrivate":false,"settingStoreCookies":true,"settingSendCookies":true,"settingDisableRenderRequestBody":false,"settingEncodeUrl":true,"settingRebuildPath":true,"settingFollowRedirects":"global","_type":"request"},{"_id":"req_defd2d9e88dc499bb439090875f18ef6","parentId":"fld_08a10223d7d7455296913aa5649d802e","modified":1642979854524,"created":1642961557299,"url":"{{ _.users_api_url }}auth","name":"login","description":"","method":"POST","body":{"mimeType":"application/json","text":"{\n  \"password\": \"user_admin\",\n  \"email\": \"user.admin@email.com\"\n}"},"parameters":[],"headers":[{"name":"Content-Type","value":"application/json","id":"pair_b8513f9144d645adb84a35402c433a5f"}],"authentication":{},"metaSortKey":-1642950152961,"isPrivate":false,"settingStoreCookies":true,"settingSendCookies":true,"settingDisableRenderRequestBody":false,"settingEncodeUrl":true,"settingRebuildPath":true,"settingFollowRedirects":"global","_type":"request"},{"_id":"req_bddbba66d8714d3382551c82c66d3fcf","parentId":"fld_e67ed24afe53486283b08dbc92449457","modified":1642979858967,"created":1642945380499,"url":"{{ _.transactions_api_url }}balance","name":"balance","description":"","method":"GET","body":{},"parameters":[],"headers":[{"id":"pair_c87d07ab046148bab5038983298bad7a","name":"Authorization","value":"Bearer {% response 'body', 'req_defd2d9e88dc499bb439090875f18ef6', 'b64::JC5hY2Nlc3NfdG9rZW4=::46b', 'when-expired', 900 %}","description":"","disabled":false}],"authentication":{},"metaSortKey":-1642945380499,"isPrivate":false,"settingStoreCookies":true,"settingSendCookies":true,"settingDisableRenderRequestBody":false,"settingEncodeUrl":true,"settingRebuildPath":true,"settingFollowRedirects":"global","_type":"request"},{"_id":"fld_e67ed24afe53486283b08dbc92449457","parentId":"wrk_98588b23176c4ecbb49eb37605ada3d7","modified":1642901526014,"created":1642901526014,"name":"Transactions","description":"","environment":{},"environmentPropertyOrder":null,"metaSortKey":-1642901526014,"_type":"request_group"},{"_id":"req_74ba993606624391bb5044c66c0d187e","parentId":"fld_e67ed24afe53486283b08dbc92449457","modified":1642979830265,"created":1642901539486,"url":"{{ _.transactions_api_url }}transactions","name":"list transactions by type user id","description":"","method":"GET","body":{},"parameters":[{"id":"pair_1c23372c1a0f41e5b4db1f8c1104850d","name":"type","value":"credit","description":""}],"headers":[{"id":"pair_2a11e20fd1b04d49be81bafe24036a84","name":"Authorization","value":"Bearer {% response 'body', 'req_defd2d9e88dc499bb439090875f18ef6', 'b64::JC5hY2Nlc3NfdG9rZW4=::46b', 'when-expired', 900 %}","description":""}],"authentication":{},"metaSortKey":-1642924008581,"isPrivate":false,"settingStoreCookies":true,"settingSendCookies":true,"settingDisableRenderRequestBody":false,"settingEncodeUrl":true,"settingRebuildPath":true,"settingFollowRedirects":"global","_type":"request"},{"_id":"req_ab3d578dc136406d81502bf53855f9a6","parentId":"fld_e67ed24afe53486283b08dbc92449457","modified":1642979892840,"created":1642902636608,"url":"{{ _.transactions_api_url }}transactions","name":"save transaction","description":"","method":"POST","body":{"mimeType":"application/json","text":"{\n\t\"user_id\": \"61ede14f77302924b82c3e80\",\n\t\"amount\": 58,\n\t\"type\": \"DEBIT\"\n}"},"parameters":[],"headers":[{"name":"Content-Type","value":"application/json","id":"pair_6e7b75966c564e6591991d0547798eff"},{"id":"pair_056ce24da3a342ecbba86de800ef2809","name":"Authorization","value":"Bearer {% response 'body', 'req_defd2d9e88dc499bb439090875f18ef6', 'b64::JC5hY2Nlc3NfdG9rZW4=::46b', 'when-expired', 900 %}","description":""}],"authentication":{},"metaSortKey":-1642902636663,"isPrivate":false,"settingStoreCookies":true,"settingSendCookies":true,"settingDisableRenderRequestBody":false,"settingEncodeUrl":true,"settingRebuildPath":true,"settingFollowRedirects":"global","_type":"request"},{"_id":"env_e49a0a7a131eb69ffed82569054a548b0cb350bd","parentId":"wrk_98588b23176c4ecbb49eb37605ada3d7","modified":1642901444970,"created":1642901441224,"name":"Base Environment","data":{},"dataPropertyOrder":{},"color":null,"isPrivate":false,"metaSortKey":1642901441224,"_type":"environment"},{"_id":"jar_e49a0a7a131eb69ffed82569054a548b0cb350bd","parentId":"wrk_98588b23176c4ecbb49eb37605ada3d7","modified":1642901441232,"created":1642901441232,"name":"Default Jar","cookies":[],"_type":"cookie_jar"},{"_id":"spc_569b2f56fb254eac9eb91214d610a1f1","parentId":"wrk_98588b23176c4ecbb49eb37605ada3d7","modified":1642901441215,"created":1642901441215,"fileName":"ilia-challenge","contents":"","contentType":"yaml","_type":"api_spec"},{"_id":"env_f1bd267ce90741c9b306313c491b1c82","parentId":"env_e49a0a7a131eb69ffed82569054a548b0cb350bd","modified":1642969804162,"created":1642901446259,"name":"Development","data":{"transactions_api_url":"http://localhost:3001/","users_api_url":"http://localhost:3002/"},"dataPropertyOrder":{"&":["transactions_api_url","users_api_url"]},"color":null,"isPrivate":false,"metaSortKey":1642901446259,"_type":"environment"}]}